lesspass/__init__.py
lesspass/cli.py
lesspass/clipboard.py
lesspass/connected.py
lesspass/core.py
lesspass/exceptions.py
lesspass/fingerprint.py
lesspass/password.py
lesspass/profile.py
lesspass/version.py
lesspass-10.2.1.dist-info/METADATA
lesspass-10.2.1.dist-info/WHEEL
lesspass-10.2.1.dist-info/entry_points.txt
lesspass-10.2.1.dist-info/top_level.txt
lesspass-10.2.1.dist-info/RECORD
