Metadata-Version: 2.1
Name: lesspass
Version: 10.2.1
Summary: LessPass stateless password generator
Home-page: https://github.com/lesspass/lesspass
Author: Guillaume Vincent
Author-email: contact@lesspass.com
License: GPL-3.0
Platform: UNKNOWN
Classifier: Programming Language :: Python
Classifier: License :: OSI Approved :: GNU General Public License v3 (GPLv3)
Classifier: Operating System :: OS Independent
Requires-Dist: requests
